jax/__init__.py
jax/ad_checkpoint.py
jax/api_util.py
jax/cloud_tpu_init.py
jax/collect_profile.py
jax/core.py
jax/custom_batching.py
jax/custom_derivatives.py
jax/custom_transpose.py
jax/debug.py
jax/distributed.py
jax/dlpack.py
jax/dtypes.py
jax/errors.py
jax/export.py
jax/ffi.py
jax/flatten_util.py
jax/memory.py
jax/monitoring.py
jax/profiler.py
jax/py.typed
jax/random.py
jax/ref.py
jax/sharding.py
jax/stages.py
jax/test_util.py
jax/tree.py
jax/tree_util.py
jax/typing.py
jax/version.py
jax/_src/__init__.py
jax/_src/abstract_arrays.py
jax/_src/ad_checkpoint.py
jax/_src/ad_util.py
jax/_src/api.py
jax/_src/api_util.py
jax/_src/array.py
jax/_src/basearray.py
jax/_src/basearray.pyi
jax/_src/blocked_sampler.py
jax/_src/buffer_callback.py
jax/_src/cache_key.py
jax/_src/callback.py
jax/_src/checkify.py
jax/_src/cloud_tpu_init.py
jax/_src/compilation_cache.py
jax/_src/compilation_cache_interface.py
jax/_src/compiler.py
jax/_src/compute_on.py
jax/_src/config.py
jax/_src/core.py
jax/_src/custom_api_util.py
jax/_src/custom_batching.py
jax/_src/custom_dce.py
jax/_src/custom_derivatives.py
jax/_src/custom_partitioning.py
jax/_src/custom_partitioning_sharding_rule.py
jax/_src/custom_transpose.py
jax/_src/debugging.py
jax/_src/deprecations.py
jax/_src/dispatch.py
jax/_src/distributed.py
jax/_src/dlpack.py
jax/_src/dtypes.py
jax/_src/earray.py
jax/_src/effects.py
jax/_src/environment_info.py
jax/_src/error_check.py
jax/_src/errors.py
jax/_src/ffi.py
jax/_src/flatten_util.py
jax/_src/frozen_dict.py
jax/_src/hardware_utils.py
jax/_src/hashable_array.py
jax/_src/hijax.py
jax/_src/jaxpr_util.py
jax/_src/lax_reference.py
jax/_src/layout.py
jax/_src/lazy_loader.py
jax/_src/linear_util.py
jax/_src/literals.py
jax/_src/logging_config.py
jax/_src/lru_cache.py
jax/_src/memory.py
jax/_src/mesh.py
jax/_src/mesh_utils.py
jax/_src/monitoring.py
jax/_src/named_sharding.py
jax/_src/op_shardings.py
jax/_src/partition_spec.py
jax/_src/path.py
jax/_src/pickle_util.py
jax/_src/pjit.py
jax-0.9.0.dist-info/licenses/AUTHORS
jax-0.9.0.dist-info/licenses/LICENSE
jax-0.9.0.dist-info/METADATA
jax-0.9.0.dist-info/WHEEL
jax-0.9.0.dist-info/top_level.txt
jax-0.9.0.dist-info/RECORD
