Metadata-Version: 2.4
Name: jax
Version: 0.9.0
Summary: Differentiate, compile, and transform Numpy code.
Home-page: https://github.com/jax-ml/jax
Author: JAX team
Author-email: jax-dev@google.com
License: Apache-2.0
Classifier: Development Status :: 5 - Production/Stable
Classifier: Programming Language :: Python :: 3.11
Classifier: Programming Language :: Python :: 3.12
Classifier: Programming Language :: Python :: 3.13
Classifier: Programming Language :: Python :: 3.14
Classifier: Programming Language :: Python :: Free Threading :: 3 - Stable
Requires-Python: >=3.11
License-File: LICENSE
License-File: AUTHORS
Requires-Dist: jaxlib<=0.9.0,>=0.9.0
Requires-Dist: ml_dtypes>=0.5.0
Requires-Dist: numpy>=2.0
Requires-Dist: opt_einsum
Requires-Dist: scipy>=1.13
Provides-Extra: minimum-jaxlib
Requires-Dist: jaxlib==0.9.0; extra == "minimum-jaxlib"
Provides-Extra: cpu
Provides-Extra: ci
Requires-Dist: jaxlib==0.8.2; extra == "ci"
Provides-Extra: tpu
Requires-Dist: jaxlib<=0.9.0,>=0.9.0; extra == "tpu"
Requires-Dist: libtpu==0.0.34.*; extra == "tpu"
Requires-Dist: requests; extra == "tpu"
Provides-Extra: cuda
Requires-Dist: jaxlib<=0.9.0,>=0.9.0; extra == "cuda"
Requires-Dist: jax-cuda12-plugin[with-cuda]<=0.9.0,>=0.9.0; extra == "cuda"
Provides-Extra: cuda12
Requires-Dist: jaxlib<=0.9.0,>=0.9.0; extra == "cuda12"
Requires-Dist: jax-cuda12-plugin[with-cuda]<=0.9.0,>=0.9.0; extra == "cuda12"
Provides-Extra: cuda13
Requires-Dist: jaxlib<=0.9.0,>=0.9.0; extra == "cuda13"
Requires-Dist: jax-cuda13-plugin[with-cuda]<=0.9.0,>=0.9.0; extra == "cuda13"
Provides-Extra: cuda12-local
Requires-Dist: jaxlib<=0.9.0,>=0.9.0; extra == "cuda12-local"
Requires-Dist: jax-cuda12-plugin<=0.9.0,>=0.9.0; extra == "cuda12-local"
Provides-Extra: cuda13-local
Requires-Dist: jaxlib<=0.9.0,>=0.9.0; extra == "cuda13-local"
Requires-Dist: jax-cuda13-plugin<=0.9.0,>=0.9.0; extra == "cuda13-local"
Provides-Extra: rocm
Requires-Dist: jaxlib<=0.9.0,>=0.9.0; extra == "rocm"
Requires-Dist: jax-rocm7-plugin<=0.9.0,>=0.9.0; extra == "rocm"
Provides-Extra: k8s
Requires-Dist: kubernetes; extra == "k8s"
Provides-Extra: xprof
Requires-Dist: xprof; extra == "xprof"
Dynamic: author
Dynamic: author-email
Dynamic: classifier
Dynamic: description
Dynamic: description-content-type
Dynamic: home-page
Dynamic: license
Dynamic: license-file
Dynamic: provides-extra
Dynamic: requires-dist
Dynamic: requires-python
Dynamic: summary
